[
  { "count" : 1013 }
, { "name" : "conv1 + conv1_relu + pool1 input reformatter 0", "timeMs" : 53.3021, "averageMs" : 0.0526181, "percentage" : 1.73547 }
, { "name" : "conv1 + conv1_relu + pool1", "timeMs" : 66.0908, "averageMs" : 0.0652426, "percentage" : 2.15185 }
, { "name" : "res2a_branch2a + res2a_branch2a_relu", "timeMs" : 29.9509, "averageMs" : 0.0295665, "percentage" : 0.975173 }
, { "name" : "res2a_branch2b + res2a_branch2b_relu", "timeMs" : 53.444, "averageMs" : 0.0527582, "percentage" : 1.74009 }
, { "name" : "res2a_branch2c", "timeMs" : 54.0293, "averageMs" : 0.0533359, "percentage" : 1.75914 }
, { "name" : "res2a_branch1 + res2a + res2a_relu", "timeMs" : 73.3577, "averageMs" : 0.0724163, "percentage" : 2.38846 }
, { "name" : "res2b_branch2a + res2b_branch2a_relu", "timeMs" : 47.4394, "averageMs" : 0.0468307, "percentage" : 1.54458 }
, { "name" : "res2b_branch2b + res2b_branch2b_relu", "timeMs" : 45.0295, "averageMs" : 0.0444516, "percentage" : 1.46612 }
, { "name" : "res2b_branch2c + res2b + res2b_relu", "timeMs" : 62.5891, "averageMs" : 0.0617859, "percentage" : 2.03784 }
, { "name" : "res2c_branch2a + res2c_branch2a_relu", "timeMs" : 40.5578, "averageMs" : 0.0400373, "percentage" : 1.32052 }
, { "name" : "res2c_branch2b + res2c_branch2b_relu", "timeMs" : 44.8224, "averageMs" : 0.0442472, "percentage" : 1.45937 }
, { "name" : "res2c_branch2c + res2c + res2c_relu", "timeMs" : 62.2113, "averageMs" : 0.0614129, "percentage" : 2.02554 }
, { "name" : "res3a_branch2a + res3a_branch2a_relu", "timeMs" : 24.2702, "averageMs" : 0.0239587, "percentage" : 0.790214 }
, { "name" : "res3a_branch2b + res3a_branch2b_relu", "timeMs" : 49.5493, "averageMs" : 0.0489134, "percentage" : 1.61328 }
, { "name" : "res3a_branch2c", "timeMs" : 41.3118, "averageMs" : 0.0407816, "percentage" : 1.34507 }
, { "name" : "res3a_branch1 + res3a + res3a_relu", "timeMs" : 63.0667, "averageMs" : 0.0622574, "percentage" : 2.05339 }
, { "name" : "res3b_branch2a + res3b_branch2a_relu", "timeMs" : 29.4162, "averageMs" : 0.0290387, "percentage" : 0.957763 }
, { "name" : "res3b_branch2b + res3b_branch2b_relu", "timeMs" : 50.201, "averageMs" : 0.0495567, "percentage" : 1.6345 }
, { "name" : "res3b_branch2c + res3b + res3b_relu", "timeMs" : 57.9064, "averageMs" : 0.0571632, "percentage" : 1.88538 }
, { "name" : "res3c_branch2a + res3c_branch2a_relu", "timeMs" : 32.3985, "averageMs" : 0.0319828, "percentage" : 1.05487 }
, { "name" : "res3c_branch2b + res3c_branch2b_relu", "timeMs" : 51.8201, "averageMs" : 0.0511551, "percentage" : 1.68721 }
, { "name" : "res3c_branch2c + res3c + res3c_relu", "timeMs" : 59.91, "averageMs" : 0.0591412, "percentage" : 1.95061 }
, { "name" : "res3d_branch2a + res3d_branch2a_relu", "timeMs" : 32.4127, "averageMs" : 0.0319967, "percentage" : 1.05533 }
, { "name" : "res3d_branch2b + res3d_branch2b_relu", "timeMs" : 52.7615, "averageMs" : 0.0520844, "percentage" : 1.71786 }
, { "name" : "res3d_branch2c + res3d + res3d_relu", "timeMs" : 57.0422, "averageMs" : 0.0563101, "percentage" : 1.85724 }
, { "name" : "res4a_branch2a + res4a_branch2a_relu", "timeMs" : 29.0087, "averageMs" : 0.0286364, "percentage" : 0.944495 }
, { "name" : "res4a_branch2b + res4a_branch2b_relu", "timeMs" : 67.3733, "averageMs" : 0.0665087, "percentage" : 2.19361 }
, { "name" : "res4a_branch2c", "timeMs" : 40.2041, "averageMs" : 0.0396881, "percentage" : 1.30901 }
, { "name" : "res4a_branch1 + res4a + res4a_relu", "timeMs" : 62.4344, "averageMs" : 0.0616332, "percentage" : 2.03281 }
, { "name" : "res4b_branch2a + res4b_branch2a_relu", "timeMs" : 37.4368, "averageMs" : 0.0369564, "percentage" : 1.21891 }
, { "name" : "res4b_branch2b + res4b_branch2b_relu", "timeMs" : 67.8157, "averageMs" : 0.0669454, "percentage" : 2.20801 }
, { "name" : "res4b_branch2c + res4b + res4b_relu", "timeMs" : 37.592, "averageMs" : 0.0371095, "percentage" : 1.22396 }
, { "name" : "res4c_branch2a + res4c_branch2a_relu", "timeMs" : 35.1492, "averageMs" : 0.0346982, "percentage" : 1.14443 }
, { "name" : "res4c_branch2b + res4c_branch2b_relu", "timeMs" : 61.7386, "averageMs" : 0.0609463, "percentage" : 2.01015 }
, { "name" : "res4c_branch2c + res4c + res4c_relu", "timeMs" : 39.0049, "averageMs" : 0.0385043, "percentage" : 1.26996 }
, { "name" : "res4d_branch2a + res4d_branch2a_relu", "timeMs" : 35.2715, "averageMs" : 0.0348189, "percentage" : 1.14841 }
, { "name" : "res4d_branch2b + res4d_branch2b_relu", "timeMs" : 62.3978, "averageMs" : 0.0615971, "percentage" : 2.03161 }
, { "name" : "res4d_branch2c + res4d + res4d_relu", "timeMs" : 37.379, "averageMs" : 0.0368994, "percentage" : 1.21703 }
, { "name" : "res4e_branch2a + res4e_branch2a_relu", "timeMs" : 35.3948, "averageMs" : 0.0349405, "percentage" : 1.15242 }
, { "name" : "res4e_branch2b + res4e_branch2b_relu", "timeMs" : 61.3839, "averageMs" : 0.0605961, "percentage" : 1.9986 }
, { "name" : "res4e_branch2c + res4e + res4e_relu", "timeMs" : 37.6775, "averageMs" : 0.037194, "percentage" : 1.22674 }
, { "name" : "res4f_branch2a + res4f_branch2a_relu", "timeMs" : 35.1421, "averageMs" : 0.0346911, "percentage" : 1.14419 }
, { "name" : "res4f_branch2b + res4f_branch2b_relu", "timeMs" : 62.6229, "averageMs" : 0.0618192, "percentage" : 2.03894 }
, { "name" : "res4f_branch2c + res4f + res4f_relu", "timeMs" : 37.8651, "averageMs" : 0.0373792, "percentage" : 1.23285 }
, { "name" : "res5a_branch2a + res5a_branch2a_relu", "timeMs" : 36.5173, "averageMs" : 0.0360486, "percentage" : 1.18897 }
, { "name" : "res5a_branch2b + res5a_branch2b_relu", "timeMs" : 109.392, "averageMs" : 0.107988, "percentage" : 3.5617 }
, { "name" : "res5a_branch2c", "timeMs" : 59.2001, "averageMs" : 0.0584403, "percentage" : 1.9275 }
, { "name" : "res5a_branch1 + res5a + res5a_relu", "timeMs" : 83.3335, "averageMs" : 0.0822641, "percentage" : 2.71326 }
, { "name" : "res5b_branch2a + res5b_branch2a_relu", "timeMs" : 57.2265, "averageMs" : 0.0564921, "percentage" : 1.86324 }
, { "name" : "res5b_branch2b + res5b_branch2b_relu", "timeMs" : 109.536, "averageMs" : 0.108131, "percentage" : 3.5664 }
, { "name" : "res5b_branch2c + res5b + res5b_relu", "timeMs" : 52.7507, "averageMs" : 0.0520737, "percentage" : 1.71751 }
, { "name" : "res5c_branch2a + res5c_branch2a_relu", "timeMs" : 57.8162, "averageMs" : 0.0570742, "percentage" : 1.88244 }
, { "name" : "res5c_branch2b + res5c_branch2b_relu", "timeMs" : 108.351, "averageMs" : 0.10696, "percentage" : 3.5278 }
, { "name" : "res5c_branch2c + res5c + res5c_relu", "timeMs" : 52.6909, "averageMs" : 0.0520147, "percentage" : 1.71557 }
, { "name" : "pool5", "timeMs" : 19.9792, "averageMs" : 0.0197228, "percentage" : 0.650504 }
, { "name" : "fc1000 input reformatter 0", "timeMs" : 8.12248, "averageMs" : 0.00801825, "percentage" : 0.26446 }
, { "name" : "fc1000", "timeMs" : 186.949, "averageMs" : 0.18455, "percentage" : 6.08688 }
, { "name" : "prob", "timeMs" : 11.6949, "averageMs" : 0.0115449, "percentage" : 0.380776 }
]
[
  { "count" : 477 }
, { "name" : "conv1 + conv1_relu + pool1 input reformatter 0", "timeMs" : 57.2403, "averageMs" : 0.120001, "percentage" : 1.84438 }
, { "name" : "conv1 + conv1_relu + pool1", "timeMs" : 96.7285, "averageMs" : 0.202785, "percentage" : 3.11676 }
, { "name" : "res2a_branch2a + res2a_branch2a_relu", "timeMs" : 28.6139, "averageMs" : 0.0599873, "percentage" : 0.921991 }
, { "name" : "res2a_branch2b + res2a_branch2b_relu", "timeMs" : 62.6539, "averageMs" : 0.13135, "percentage" : 2.01882 }
, { "name" : "res2a_branch2c", "timeMs" : 74.5342, "averageMs" : 0.156256, "percentage" : 2.40162 }
, { "name" : "res2a_branch1 + res2a + res2a_relu", "timeMs" : 101.462, "averageMs" : 0.212708, "percentage" : 3.26927 }
, { "name" : "res2b_branch2a + res2b_branch2a_relu", "timeMs" : 58.4552, "averageMs" : 0.122548, "percentage" : 1.88353 }
, { "name" : "res2b_branch2b + res2b_branch2b_relu", "timeMs" : 64.8151, "averageMs" : 0.135881, "percentage" : 2.08845 }
, { "name" : "res2b_branch2c + res2b + res2b_relu", "timeMs" : 101.995, "averageMs" : 0.213826, "percentage" : 3.28646 }
, { "name" : "res2c_branch2a + res2c_branch2a_relu", "timeMs" : 58.294, "averageMs" : 0.12221, "percentage" : 1.87833 }
, { "name" : "res2c_branch2b + res2c_branch2b_relu", "timeMs" : 62.7936, "averageMs" : 0.131643, "percentage" : 2.02332 }
, { "name" : "res2c_branch2c + res2c + res2c_relu", "timeMs" : 101.92, "averageMs" : 0.213669, "percentage" : 3.28404 }
, { "name" : "res3a_branch2a + res3a_branch2a_relu", "timeMs" : 27.4641, "averageMs" : 0.0575768, "percentage" : 0.884941 }
, { "name" : "res3a_branch2b + res3a_branch2b_relu", "timeMs" : 55.9233, "averageMs" : 0.11724, "percentage" : 1.80195 }
, { "name" : "res3a_branch2c", "timeMs" : 53.572, "averageMs" : 0.11231, "percentage" : 1.72618 }
, { "name" : "res3a_branch1 + res3a + res3a_relu", "timeMs" : 82.6212, "averageMs" : 0.17321, "percentage" : 2.6622 }
, { "name" : "res3b_branch2a + res3b_branch2a_relu", "timeMs" : 37.4011, "averageMs" : 0.0784091, "percentage" : 1.20513 }
, { "name" : "res3b_branch2b + res3b_branch2b_relu", "timeMs" : 55.6015, "averageMs" : 0.116565, "percentage" : 1.79158 }
, { "name" : "res3b_branch2c + res3b + res3b_relu", "timeMs" : 62.4831, "averageMs" : 0.130992, "percentage" : 2.01331 }
, { "name" : "res3c_branch2a + res3c_branch2a_relu", "timeMs" : 37.3224, "averageMs" : 0.0782441, "percentage" : 1.20259 }
, { "name" : "res3c_branch2b + res3c_branch2b_relu", "timeMs" : 55.5564, "averageMs" : 0.11647, "percentage" : 1.79012 }
, { "name" : "res3c_branch2c + res3c + res3c_relu", "timeMs" : 61.845, "averageMs" : 0.129654, "percentage" : 1.99275 }
, { "name" : "res3d_branch2a + res3d_branch2a_relu", "timeMs" : 37.8595, "averageMs" : 0.07937, "percentage" : 1.2199 }
, { "name" : "res3d_branch2b + res3d_branch2b_relu", "timeMs" : 56.2866, "averageMs" : 0.118001, "percentage" : 1.81365 }
, { "name" : "res3d_branch2c + res3d + res3d_relu", "timeMs" : 62.0782, "averageMs" : 0.130143, "percentage" : 2.00027 }
, { "name" : "res4a_branch2a + res4a_branch2a_relu", "timeMs" : 23.0496, "averageMs" : 0.048322, "percentage" : 0.742697 }
, { "name" : "res4a_branch2b + res4a_branch2b_relu", "timeMs" : 65.2, "averageMs" : 0.136688, "percentage" : 2.10086 }
, { "name" : "res4a_branch2c", "timeMs" : 38.9578, "averageMs" : 0.0816725, "percentage" : 1.25529 }
, { "name" : "res4a_branch1 + res4a + res4a_relu", "timeMs" : 67.2856, "averageMs" : 0.14106, "percentage" : 2.16806 }
, { "name" : "res4b_branch2a + res4b_branch2a_relu", "timeMs" : 34.9344, "averageMs" : 0.0732376, "percentage" : 1.12565 }
, { "name" : "res4b_branch2b + res4b_branch2b_relu", "timeMs" : 64.7161, "averageMs" : 0.135673, "percentage" : 2.08526 }
, { "name" : "res4b_branch2c + res4b + res4b_relu", "timeMs" : 47.3263, "averageMs" : 0.0992166, "percentage" : 1.52494 }
, { "name" : "res4c_branch2a + res4c_branch2a_relu", "timeMs" : 37.9627, "averageMs" : 0.0795863, "percentage" : 1.22322 }
, { "name" : "res4c_branch2b + res4c_branch2b_relu", "timeMs" : 65.0868, "averageMs" : 0.13645, "percentage" : 2.09721 }
, { "name" : "res4c_branch2c + res4c + res4c_relu", "timeMs" : 47.2402, "averageMs" : 0.0990361, "percentage" : 1.52216 }
, { "name" : "res4d_branch2a + res4d_branch2a_relu", "timeMs" : 35.6173, "averageMs" : 0.0746693, "percentage" : 1.14765 }
, { "name" : "res4d_branch2b + res4d_branch2b_relu", "timeMs" : 64.6981, "averageMs" : 0.135635, "percentage" : 2.08468 }
, { "name" : "res4d_branch2c + res4d + res4d_relu", "timeMs" : 47.1852, "averageMs" : 0.0989207, "percentage" : 1.52039 }
, { "name" : "res4e_branch2a + res4e_branch2a_relu", "timeMs" : 35.6817, "averageMs" : 0.0748045, "percentage" : 1.14973 }
, { "name" : "res4e_branch2b + res4e_branch2b_relu", "timeMs" : 64.6284, "averageMs" : 0.135489, "percentage" : 2.08244 }
, { "name" : "res4e_branch2c + res4e + res4e_relu", "timeMs" : 47.3036, "averageMs" : 0.099169, "percentage" : 1.5242 }
, { "name" : "res4f_branch2a + res4f_branch2a_relu", "timeMs" : 35.5743, "averageMs" : 0.0745793, "percentage" : 1.14627 }
, { "name" : "res4f_branch2b + res4f_branch2b_relu", "timeMs" : 65.2356, "averageMs" : 0.136762, "percentage" : 2.102 }
, { "name" : "res4f_branch2c + res4f + res4f_relu", "timeMs" : 48.6278, "averageMs" : 0.101945, "percentage" : 1.56687 }
, { "name" : "res5a_branch2a + res5a_branch2a_relu", "timeMs" : 22.2417, "averageMs" : 0.0466284, "percentage" : 0.716667 }
, { "name" : "res5a_branch2b + res5a_branch2b_relu", "timeMs" : 71.7535, "averageMs" : 0.150427, "percentage" : 2.31202 }
, { "name" : "res5a_branch2c", "timeMs" : 35.8768, "averageMs" : 0.0752133, "percentage" : 1.15601 }
, { "name" : "res5a_branch1 + res5a + res5a_relu", "timeMs" : 63.7641, "averageMs" : 0.133677, "percentage" : 2.05459 }
, { "name" : "res5b_branch2a + res5b_branch2a_relu", "timeMs" : 36.2761, "averageMs" : 0.0760505, "percentage" : 1.16888 }
, { "name" : "res5b_branch2b + res5b_branch2b_relu", "timeMs" : 71.6044, "averageMs" : 0.150114, "percentage" : 2.30722 }
, { "name" : "res5b_branch2c + res5b + res5b_relu", "timeMs" : 40.3474, "averageMs" : 0.0845857, "percentage" : 1.30006 }
, { "name" : "res5c_branch2a + res5c_branch2a_relu", "timeMs" : 36.4141, "averageMs" : 0.0763398, "percentage" : 1.17332 }
, { "name" : "res5c_branch2b + res5c_branch2b_relu", "timeMs" : 73.2234, "averageMs" : 0.153508, "percentage" : 2.35938 }
, { "name" : "res5c_branch2c + res5c + res5c_relu", "timeMs" : 40.9503, "averageMs" : 0.0858497, "percentage" : 1.31949 }
, { "name" : "pool5", "timeMs" : 18.3814, "averageMs" : 0.0385355, "percentage" : 0.592281 }
, { "name" : "fc1000 input reformatter 0", "timeMs" : 4.19293, "averageMs" : 0.00879021, "percentage" : 0.135103 }
, { "name" : "fc1000", "timeMs" : 91.4, "averageMs" : 0.191614, "percentage" : 2.94507 }
, { "name" : "prob", "timeMs" : 5.23901, "averageMs" : 0.0109832, "percentage" : 0.16881 }
]
[
  { "count" : 282 }
, { "name" : "conv1 + conv1_relu + pool1 input reformatter 0", "timeMs" : 62.5579, "averageMs" : 0.221837, "percentage" : 1.9961 }
, { "name" : "conv1 + conv1_relu + pool1", "timeMs" : 107.413, "averageMs" : 0.380897, "percentage" : 3.42734 }
, { "name" : "res2a_branch2a + res2a_branch2a_relu", "timeMs" : 27.585, "averageMs" : 0.0978192, "percentage" : 0.880185 }
, { "name" : "res2a_branch2b + res2a_branch2b_relu", "timeMs" : 63.6235, "averageMs" : 0.225615, "percentage" : 2.03011 }
, { "name" : "res2a_branch2c", "timeMs" : 85.367, "averageMs" : 0.30272, "percentage" : 2.7239 }
, { "name" : "res2a_branch1 + res2a + res2a_relu", "timeMs" : 114.797, "averageMs" : 0.407082, "percentage" : 3.66296 }
, { "name" : "res2b_branch2a + res2b_branch2a_relu", "timeMs" : 59.0227, "averageMs" : 0.2093, "percentage" : 1.8833 }
, { "name" : "res2b_branch2b + res2b_branch2b_relu", "timeMs" : 67.4674, "averageMs" : 0.239246, "percentage" : 2.15276 }
, { "name" : "res2b_branch2c + res2b + res2b_relu", "timeMs" : 113.636, "averageMs" : 0.402965, "percentage" : 3.62592 }
, { "name" : "res2c_branch2a + res2c_branch2a_relu", "timeMs" : 58.5329, "averageMs" : 0.207564, "percentage" : 1.86768 }
, { "name" : "res2c_branch2b + res2c_branch2b_relu", "timeMs" : 65.522, "averageMs" : 0.232347, "percentage" : 2.09068 }
, { "name" : "res2c_branch2c + res2c + res2c_relu", "timeMs" : 115.197, "averageMs" : 0.4085, "percentage" : 3.67572 }
, { "name" : "res3a_branch2a + res3a_branch2a_relu", "timeMs" : 26.8757, "averageMs" : 0.095304, "percentage" : 0.857553 }
, { "name" : "res3a_branch2b + res3a_branch2b_relu", "timeMs" : 56.7622, "averageMs" : 0.201284, "percentage" : 1.81117 }
, { "name" : "res3a_branch2c", "timeMs" : 54.9822, "averageMs" : 0.194972, "percentage" : 1.75438 }
, { "name" : "res3a_branch1 + res3a + res3a_relu", "timeMs" : 92.917, "averageMs" : 0.329493, "percentage" : 2.9648 }
, { "name" : "res3b_branch2a + res3b_branch2a_relu", "timeMs" : 37.8134, "averageMs" : 0.13409, "percentage" : 1.20655 }
, { "name" : "res3b_branch2b + res3b_branch2b_relu", "timeMs" : 56.7617, "averageMs" : 0.201283, "percentage" : 1.81116 }
, { "name" : "res3b_branch2c + res3b + res3b_relu", "timeMs" : 66.6525, "averageMs" : 0.236356, "percentage" : 2.12675 }
, { "name" : "res3c_branch2a + res3c_branch2a_relu", "timeMs" : 38.2627, "averageMs" : 0.135683, "percentage" : 1.22089 }
, { "name" : "res3c_branch2b + res3c_branch2b_relu", "timeMs" : 57.5662, "averageMs" : 0.204135, "percentage" : 1.83683 }
, { "name" : "res3c_branch2c + res3c + res3c_relu", "timeMs" : 66.9856, "averageMs" : 0.237538, "percentage" : 2.13738 }
, { "name" : "res3d_branch2a + res3d_branch2a_relu", "timeMs" : 38.0171, "averageMs" : 0.134812, "percentage" : 1.21305 }
, { "name" : "res3d_branch2b + res3d_branch2b_relu", "timeMs" : 56.6174, "averageMs" : 0.200771, "percentage" : 1.80655 }
, { "name" : "res3d_branch2c + res3d + res3d_relu", "timeMs" : 67.4568, "averageMs" : 0.239208, "percentage" : 2.15242 }
, { "name" : "res4a_branch2a + res4a_branch2a_relu", "timeMs" : 20.6113, "averageMs" : 0.0730898, "percentage" : 0.657669 }
, { "name" : "res4a_branch2b + res4a_branch2b_relu", "timeMs" : 59.861, "averageMs" : 0.212273, "percentage" : 1.91005 }
, { "name" : "res4a_branch2c", "timeMs" : 40.5556, "averageMs" : 0.143814, "percentage" : 1.29405 }
, { "name" : "res4a_branch1 + res4a + res4a_relu", "timeMs" : 69.4096, "averageMs" : 0.246133, "percentage" : 2.21473 }
, { "name" : "res4b_branch2a + res4b_branch2a_relu", "timeMs" : 32.0474, "averageMs" : 0.113643, "percentage" : 1.02257 }
, { "name" : "res4b_branch2b + res4b_branch2b_relu", "timeMs" : 60.4637, "averageMs" : 0.21441, "percentage" : 1.92928 }
, { "name" : "res4b_branch2c + res4b + res4b_relu", "timeMs" : 48.5655, "averageMs" : 0.172218, "percentage" : 1.54963 }
, { "name" : "res4c_branch2a + res4c_branch2a_relu", "timeMs" : 32.3923, "averageMs" : 0.114866, "percentage" : 1.03358 }
, { "name" : "res4c_branch2b + res4c_branch2b_relu", "timeMs" : 59.8459, "averageMs" : 0.21222, "percentage" : 1.90957 }
, { "name" : "res4c_branch2c + res4c + res4c_relu", "timeMs" : 48.2141, "averageMs" : 0.170972, "percentage" : 1.53842 }
, { "name" : "res4d_branch2a + res4d_branch2a_relu", "timeMs" : 32.1182, "averageMs" : 0.113894, "percentage" : 1.02483 }
, { "name" : "res4d_branch2b + res4d_branch2b_relu", "timeMs" : 59.7994, "averageMs" : 0.212054, "percentage" : 1.90808 }
, { "name" : "res4d_branch2c + res4d + res4d_relu", "timeMs" : 48.371, "averageMs" : 0.171528, "percentage" : 1.54343 }
, { "name" : "res4e_branch2a + res4e_branch2a_relu", "timeMs" : 33.6682, "averageMs" : 0.119391, "percentage" : 1.07429 }
, { "name" : "res4e_branch2b + res4e_branch2b_relu", "timeMs" : 60.2244, "averageMs" : 0.213562, "percentage" : 1.92165 }
, { "name" : "res4e_branch2c + res4e + res4e_relu", "timeMs" : 48.5345, "averageMs" : 0.172108, "percentage" : 1.54864 }
, { "name" : "res4f_branch2a + res4f_branch2a_relu", "timeMs" : 32.0795, "averageMs" : 0.113757, "percentage" : 1.0236 }
, { "name" : "res4f_branch2b + res4f_branch2b_relu", "timeMs" : 59.7175, "averageMs" : 0.211764, "percentage" : 1.90547 }
, { "name" : "res4f_branch2c + res4f + res4f_relu", "timeMs" : 48.5935, "averageMs" : 0.172317, "percentage" : 1.55053 }
, { "name" : "res5a_branch2a + res5a_branch2a_relu", "timeMs" : 21.9734, "averageMs" : 0.0779199, "percentage" : 0.70113 }
, { "name" : "res5a_branch2b + res5a_branch2b_relu", "timeMs" : 71.3956, "averageMs" : 0.253176, "percentage" : 2.2781 }
, { "name" : "res5a_branch2c", "timeMs" : 38.4773, "averageMs" : 0.136444, "percentage" : 1.22774 }
, { "name" : "res5a_branch1 + res5a + res5a_relu", "timeMs" : 70.3024, "averageMs" : 0.249299, "percentage" : 2.24322 }
, { "name" : "res5b_branch2a + res5b_branch2a_relu", "timeMs" : 36.8068, "averageMs" : 0.130521, "percentage" : 1.17444 }
, { "name" : "res5b_branch2b + res5b_branch2b_relu", "timeMs" : 71.3313, "averageMs" : 0.252948, "percentage" : 2.27605 }
, { "name" : "res5b_branch2c + res5b + res5b_relu", "timeMs" : 43.0598, "averageMs" : 0.152694, "percentage" : 1.37396 }
, { "name" : "res5c_branch2a + res5c_branch2a_relu", "timeMs" : 37.2141, "averageMs" : 0.131965, "percentage" : 1.18743 }
, { "name" : "res5c_branch2b + res5c_branch2b_relu", "timeMs" : 70.785, "averageMs" : 0.251011, "percentage" : 2.25862 }
, { "name" : "res5c_branch2c + res5c + res5c_relu", "timeMs" : 42.9229, "averageMs" : 0.152209, "percentage" : 1.36959 }
, { "name" : "pool5", "timeMs" : 13.2763, "averageMs" : 0.047079, "percentage" : 0.423621 }
, { "name" : "fc1000 input reformatter 0", "timeMs" : 3.09149, "averageMs" : 0.0109627, "percentage" : 0.0986435 }
, { "name" : "fc1000", "timeMs" : 56.7494, "averageMs" : 0.201239, "percentage" : 1.81077 }
, { "name" : "prob", "timeMs" : 3.14899, "averageMs" : 0.0111666, "percentage" : 0.100478 }
]
[
  { "count" : 146 }
, { "name" : "conv1 + conv1_relu + pool1 input reformatter 0", "timeMs" : 65.0441, "averageMs" : 0.445507, "percentage" : 2.06847 }
, { "name" : "conv1 + conv1_relu + pool1", "timeMs" : 115.06, "averageMs" : 0.788085, "percentage" : 3.65904 }
, { "name" : "res2a_branch2a + res2a_branch2a_relu", "timeMs" : 25.1456, "averageMs" : 0.17223, "percentage" : 0.799658 }
, { "name" : "res2a_branch2b + res2a_branch2b_relu", "timeMs" : 64.297, "averageMs" : 0.440391, "percentage" : 2.04471 }
, { "name" : "res2a_branch2c", "timeMs" : 98.9329, "averageMs" : 0.677623, "percentage" : 3.14617 }
, { "name" : "res2a_branch1 + res2a + res2a_relu", "timeMs" : 127.709, "averageMs" : 0.874718, "percentage" : 4.06128 }
, { "name" : "res2b_branch2a + res2b_branch2a_relu", "timeMs" : 55.4726, "averageMs" : 0.379949, "percentage" : 1.76409 }
, { "name" : "res2b_branch2b + res2b_branch2b_relu", "timeMs" : 63.5168, "averageMs" : 0.435047, "percentage" : 2.0199 }
, { "name" : "res2b_branch2c + res2b + res2b_relu", "timeMs" : 124.371, "averageMs" : 0.851853, "percentage" : 3.95512 }
, { "name" : "res2c_branch2a + res2c_branch2a_relu", "timeMs" : 60.0608, "averageMs" : 0.411375, "percentage" : 1.91 }
, { "name" : "res2c_branch2b + res2c_branch2b_relu", "timeMs" : 67.8425, "averageMs" : 0.464675, "percentage" : 2.15746 }
, { "name" : "res2c_branch2c + res2c + res2c_relu", "timeMs" : 129.731, "averageMs" : 0.888568, "percentage" : 4.12558 }
, { "name" : "res3a_branch2a + res3a_branch2a_relu", "timeMs" : 24.0065, "averageMs" : 0.164428, "percentage" : 0.763433 }
, { "name" : "res3a_branch2b + res3a_branch2b_relu", "timeMs" : 53.8719, "averageMs" : 0.368985, "percentage" : 1.71318 }
, { "name" : "res3a_branch2c", "timeMs" : 69.2363, "averageMs" : 0.474221, "percentage" : 2.20179 }
, { "name" : "res3a_branch1 + res3a + res3a_relu", "timeMs" : 91.8142, "averageMs" : 0.628864, "percentage" : 2.91979 }
, { "name" : "res3b_branch2a + res3b_branch2a_relu", "timeMs" : 39.0924, "averageMs" : 0.267756, "percentage" : 1.24318 }
, { "name" : "res3b_branch2b + res3b_branch2b_relu", "timeMs" : 56.2681, "averageMs" : 0.385398, "percentage" : 1.78939 }
, { "name" : "res3b_branch2c + res3b + res3b_relu", "timeMs" : 67.173, "averageMs" : 0.460089, "percentage" : 2.13617 }
, { "name" : "res3c_branch2a + res3c_branch2a_relu", "timeMs" : 43.1804, "averageMs" : 0.295756, "percentage" : 1.37318 }
, { "name" : "res3c_branch2b + res3c_branch2b_relu", "timeMs" : 57.7602, "averageMs" : 0.395618, "percentage" : 1.83684 }
, { "name" : "res3c_branch2c + res3c + res3c_relu", "timeMs" : 67.4563, "averageMs" : 0.462029, "percentage" : 2.14518 }
, { "name" : "res3d_branch2a + res3d_branch2a_relu", "timeMs" : 44.2576, "averageMs" : 0.303134, "percentage" : 1.40744 }
, { "name" : "res3d_branch2b + res3d_branch2b_relu", "timeMs" : 54.5747, "averageMs" : 0.373799, "percentage" : 1.73553 }
, { "name" : "res3d_branch2c + res3d + res3d_relu", "timeMs" : 69.2729, "averageMs" : 0.474472, "percentage" : 2.20295 }
, { "name" : "res4a_branch2a + res4a_branch2a_relu", "timeMs" : 24.0449, "averageMs" : 0.164691, "percentage" : 0.764652 }
, { "name" : "res4a_branch2b + res4a_branch2b_relu", "timeMs" : 63.0441, "averageMs" : 0.431809, "percentage" : 2.00487 }
, { "name" : "res4a_branch2c", "timeMs" : 39.2756, "averageMs" : 0.269011, "percentage" : 1.249 }
, { "name" : "res4a_branch1 + res4a + res4a_relu", "timeMs" : 83.0303, "averageMs" : 0.568701, "percentage" : 2.64045 }
, { "name" : "res4b_branch2a + res4b_branch2a_relu", "timeMs" : 29.5762, "averageMs" : 0.202577, "percentage" : 0.940554 }
, { "name" : "res4b_branch2b + res4b_branch2b_relu", "timeMs" : 54.0983, "averageMs" : 0.370536, "percentage" : 1.72038 }
, { "name" : "res4b_branch2c + res4b + res4b_relu", "timeMs" : 51.2385, "averageMs" : 0.350949, "percentage" : 1.62944 }
, { "name" : "res4c_branch2a + res4c_branch2a_relu", "timeMs" : 32.9054, "averageMs" : 0.22538, "percentage" : 1.04643 }
, { "name" : "res4c_branch2b + res4c_branch2b_relu", "timeMs" : 55.0399, "averageMs" : 0.376986, "percentage" : 1.75033 }
, { "name" : "res4c_branch2c + res4c + res4c_relu", "timeMs" : 49.4079, "averageMs" : 0.338411, "percentage" : 1.57123 }
, { "name" : "res4d_branch2a + res4d_branch2a_relu", "timeMs" : 32.9924, "averageMs" : 0.225975, "percentage" : 1.04919 }
, { "name" : "res4d_branch2b + res4d_branch2b_relu", "timeMs" : 56.3045, "averageMs" : 0.385647, "percentage" : 1.79054 }
, { "name" : "res4d_branch2c + res4d + res4d_relu", "timeMs" : 46.7395, "averageMs" : 0.320133, "percentage" : 1.48636 }
, { "name" : "res4e_branch2a + res4e_branch2a_relu", "timeMs" : 31.32, "averageMs" : 0.214521, "percentage" : 0.996009 }
, { "name" : "res4e_branch2b + res4e_branch2b_relu", "timeMs" : 60.4905, "averageMs" : 0.414319, "percentage" : 1.92366 }
, { "name" : "res4e_branch2c + res4e + res4e_relu", "timeMs" : 47.0491, "averageMs" : 0.322254, "percentage" : 1.49621 }
, { "name" : "res4f_branch2a + res4f_branch2a_relu", "timeMs" : 29.7103, "averageMs" : 0.203495, "percentage" : 0.944819 }
, { "name" : "res4f_branch2b + res4f_branch2b_relu", "timeMs" : 61.8827, "averageMs" : 0.423854, "percentage" : 1.96793 }
, { "name" : "res4f_branch2c + res4f + res4f_relu", "timeMs" : 48.1999, "averageMs" : 0.330137, "percentage" : 1.53281 }
, { "name" : "res5a_branch2a + res5a_branch2a_relu", "timeMs" : 17.7206, "averageMs" : 0.121374, "percentage" : 0.563534 }
, { "name" : "res5a_branch2b + res5a_branch2b_relu", "timeMs" : 71.1625, "averageMs" : 0.487414, "percentage" : 2.26304 }
, { "name" : "res5a_branch2c", "timeMs" : 39.5541, "averageMs" : 0.270919, "percentage" : 1.25786 }
, { "name" : "res5a_branch1 + res5a + res5a_relu", "timeMs" : 63.2022, "averageMs" : 0.432892, "percentage" : 2.0099 }
, { "name" : "res5b_branch2a + res5b_branch2a_relu", "timeMs" : 32.7389, "averageMs" : 0.224239, "percentage" : 1.04113 }
, { "name" : "res5b_branch2b + res5b_branch2b_relu", "timeMs" : 64.0709, "averageMs" : 0.438842, "percentage" : 2.03752 }
, { "name" : "res5b_branch2c + res5b + res5b_relu", "timeMs" : 38.4926, "averageMs" : 0.263648, "percentage" : 1.22411 }
, { "name" : "res5c_branch2a + res5c_branch2a_relu", "timeMs" : 31.1343, "averageMs" : 0.213249, "percentage" : 0.990105 }
, { "name" : "res5c_branch2b + res5c_branch2b_relu", "timeMs" : 65.3586, "averageMs" : 0.447661, "percentage" : 2.07847 }
, { "name" : "res5c_branch2c + res5c + res5c_relu", "timeMs" : 40.6246, "averageMs" : 0.278251, "percentage" : 1.29191 }
, { "name" : "pool5", "timeMs" : 9.86537, "averageMs" : 0.0675711, "percentage" : 0.313729 }
, { "name" : "fc1000 input reformatter 0", "timeMs" : 1.94326, "averageMs" : 0.01331, "percentage" : 0.0617978 }
, { "name" : "fc1000", "timeMs" : 35.502, "averageMs" : 0.243165, "percentage" : 1.129 }
, { "name" : "prob", "timeMs" : 1.6808, "averageMs" : 0.0115123, "percentage" : 0.0534512 }
]
[
  { "count" : 80 }
, { "name" : "conv1 + conv1_relu + pool1 input reformatter 0", "timeMs" : 73.1072, "averageMs" : 0.91384, "percentage" : 2.30972 }
, { "name" : "conv1 + conv1_relu + pool1", "timeMs" : 122.706, "averageMs" : 1.53383, "percentage" : 3.87673 }
, { "name" : "res2a_branch2a + res2a_branch2a_relu", "timeMs" : 25.5041, "averageMs" : 0.318802, "percentage" : 0.805767 }
, { "name" : "res2a_branch2b + res2a_branch2b_relu", "timeMs" : 69.6885, "averageMs" : 0.871107, "percentage" : 2.20171 }
, { "name" : "res2a_branch2c", "timeMs" : 92.8458, "averageMs" : 1.16057, "percentage" : 2.93333 }
, { "name" : "res2a_branch1 + res2a + res2a_relu", "timeMs" : 129.221, "averageMs" : 1.61526, "percentage" : 4.08255 }
, { "name" : "res2b_branch2a + res2b_branch2a_relu", "timeMs" : 60.1065, "averageMs" : 0.751332, "percentage" : 1.89898 }
, { "name" : "res2b_branch2b + res2b_branch2b_relu", "timeMs" : 71.8762, "averageMs" : 0.898452, "percentage" : 2.27083 }
, { "name" : "res2b_branch2c + res2b + res2b_relu", "timeMs" : 135.605, "averageMs" : 1.69506, "percentage" : 4.28423 }
, { "name" : "res2c_branch2a + res2c_branch2a_relu", "timeMs" : 59.0368, "averageMs" : 0.737961, "percentage" : 1.86519 }
, { "name" : "res2c_branch2b + res2c_branch2b_relu", "timeMs" : 72.9904, "averageMs" : 0.912379, "percentage" : 2.30603 }
, { "name" : "res2c_branch2c + res2c + res2c_relu", "timeMs" : 135.038, "averageMs" : 1.68797, "percentage" : 4.26633 }
, { "name" : "res3a_branch2a + res3a_branch2a_relu", "timeMs" : 24.4442, "averageMs" : 0.305552, "percentage" : 0.77228 }
, { "name" : "res3a_branch2b + res3a_branch2b_relu", "timeMs" : 60.4654, "averageMs" : 0.755818, "percentage" : 1.91032 }
, { "name" : "res3a_branch2c", "timeMs" : 62.2218, "averageMs" : 0.777772, "percentage" : 1.96581 }
, { "name" : "res3a_branch1 + res3a + res3a_relu", "timeMs" : 104.541, "averageMs" : 1.30676, "percentage" : 3.30281 }
, { "name" : "res3b_branch2a + res3b_branch2a_relu", "timeMs" : 40.3063, "averageMs" : 0.503828, "percentage" : 1.27342 }
, { "name" : "res3b_branch2b + res3b_branch2b_relu", "timeMs" : 57.858, "averageMs" : 0.723225, "percentage" : 1.82794 }
, { "name" : "res3b_branch2c + res3b + res3b_relu", "timeMs" : 75.0268, "averageMs" : 0.937835, "percentage" : 2.37037 }
, { "name" : "res3c_branch2a + res3c_branch2a_relu", "timeMs" : 39.4928, "averageMs" : 0.49366, "percentage" : 1.24772 }
, { "name" : "res3c_branch2b + res3c_branch2b_relu", "timeMs" : 60.5824, "averageMs" : 0.75728, "percentage" : 1.91401 }
, { "name" : "res3c_branch2c + res3c + res3c_relu", "timeMs" : 73.6312, "averageMs" : 0.92039, "percentage" : 2.32627 }
, { "name" : "res3d_branch2a + res3d_branch2a_relu", "timeMs" : 39.5251, "averageMs" : 0.494063, "percentage" : 1.24874 }
, { "name" : "res3d_branch2b + res3d_branch2b_relu", "timeMs" : 59.0607, "averageMs" : 0.738258, "percentage" : 1.86594 }
, { "name" : "res3d_branch2c + res3d + res3d_relu", "timeMs" : 75.482, "averageMs" : 0.943525, "percentage" : 2.38475 }
, { "name" : "res4a_branch2a + res4a_branch2a_relu", "timeMs" : 18.3758, "averageMs" : 0.229698, "percentage" : 0.580558 }
, { "name" : "res4a_branch2b + res4a_branch2b_relu", "timeMs" : 56.2601, "averageMs" : 0.703251, "percentage" : 1.77746 }
, { "name" : "res4a_branch2c", "timeMs" : 41.2914, "averageMs" : 0.516143, "percentage" : 1.30454 }
, { "name" : "res4a_branch1 + res4a + res4a_relu", "timeMs" : 73.5085, "averageMs" : 0.918856, "percentage" : 2.3224 }
, { "name" : "res4b_branch2a + res4b_branch2a_relu", "timeMs" : 30.4143, "averageMs" : 0.380179, "percentage" : 0.960897 }
, { "name" : "res4b_branch2b + res4b_branch2b_relu", "timeMs" : 56.012, "averageMs" : 0.70015, "percentage" : 1.76962 }
, { "name" : "res4b_branch2c + res4b + res4b_relu", "timeMs" : 52.754, "averageMs" : 0.659425, "percentage" : 1.66669 }
, { "name" : "res4c_branch2a + res4c_branch2a_relu", "timeMs" : 28.9328, "averageMs" : 0.36166, "percentage" : 0.914092 }
, { "name" : "res4c_branch2b + res4c_branch2b_relu", "timeMs" : 56.5204, "averageMs" : 0.706505, "percentage" : 1.78568 }
, { "name" : "res4c_branch2c + res4c + res4c_relu", "timeMs" : 50.9759, "averageMs" : 0.637199, "percentage" : 1.61051 }
, { "name" : "res4d_branch2a + res4d_branch2a_relu", "timeMs" : 30.3109, "averageMs" : 0.378887, "percentage" : 0.957631 }
, { "name" : "res4d_branch2b + res4d_branch2b_relu", "timeMs" : 57.7115, "averageMs" : 0.721394, "percentage" : 1.82331 }
, { "name" : "res4d_branch2c + res4d + res4d_relu", "timeMs" : 51.6709, "averageMs" : 0.645886, "percentage" : 1.63247 }
, { "name" : "res4e_branch2a + res4e_branch2a_relu", "timeMs" : 29.2448, "averageMs" : 0.36556, "percentage" : 0.923947 }
, { "name" : "res4e_branch2b + res4e_branch2b_relu", "timeMs" : 56.3807, "averageMs" : 0.704759, "percentage" : 1.78127 }
, { "name" : "res4e_branch2c + res4e + res4e_relu", "timeMs" : 51.7572, "averageMs" : 0.646965, "percentage" : 1.6352 }
, { "name" : "res4f_branch2a + res4f_branch2a_relu", "timeMs" : 30.897, "averageMs" : 0.386212, "percentage" : 0.976146 }
, { "name" : "res4f_branch2b + res4f_branch2b_relu", "timeMs" : 56.7395, "averageMs" : 0.709244, "percentage" : 1.7926 }
, { "name" : "res4f_branch2c + res4f + res4f_relu", "timeMs" : 50.9399, "averageMs" : 0.636749, "percentage" : 1.60938 }
, { "name" : "res5a_branch2a + res5a_branch2a_relu", "timeMs" : 17.4571, "averageMs" : 0.218214, "percentage" : 0.551533 }
, { "name" : "res5a_branch2b + res5a_branch2b_relu", "timeMs" : 58.5172, "averageMs" : 0.731465, "percentage" : 1.84877 }
, { "name" : "res5a_branch2c", "timeMs" : 34.8117, "averageMs" : 0.435146, "percentage" : 1.09983 }
, { "name" : "res5a_branch1 + res5a + res5a_relu", "timeMs" : 66.0236, "averageMs" : 0.825295, "percentage" : 2.08592 }
, { "name" : "res5b_branch2a + res5b_branch2a_relu", "timeMs" : 29.5747, "averageMs" : 0.369684, "percentage" : 0.934371 }
, { "name" : "res5b_branch2b + res5b_branch2b_relu", "timeMs" : 59.2989, "averageMs" : 0.741236, "percentage" : 1.87346 }
, { "name" : "res5b_branch2c + res5b + res5b_relu", "timeMs" : 38.0876, "averageMs" : 0.476095, "percentage" : 1.20332 }
, { "name" : "res5c_branch2a + res5c_branch2a_relu", "timeMs" : 29.1553, "averageMs" : 0.364441, "percentage" : 0.92112 }
, { "name" : "res5c_branch2b + res5c_branch2b_relu", "timeMs" : 57.949, "averageMs" : 0.724363, "percentage" : 1.83082 }
, { "name" : "res5c_branch2c + res5c + res5c_relu", "timeMs" : 40.4226, "averageMs" : 0.505283, "percentage" : 1.2771 }
, { "name" : "pool5", "timeMs" : 11.6508, "averageMs" : 0.145636, "percentage" : 0.368092 }
, { "name" : "fc1000 input reformatter 0", "timeMs" : 1.58678, "averageMs" : 0.0198348, "percentage" : 0.0501322 }
, { "name" : "fc1000", "timeMs" : 18.3616, "averageMs" : 0.22952, "percentage" : 0.580108 }
, { "name" : "prob", "timeMs" : 1.24272, "averageMs" : 0.015534, "percentage" : 0.039262 }
]
[
  { "count" : 45 }
, { "name" : "conv1 + conv1_relu + pool1 input reformatter 0", "timeMs" : 76.3668, "averageMs" : 1.69704, "percentage" : 2.30635 }
, { "name" : "conv1 + conv1_relu + pool1", "timeMs" : 127.519, "averageMs" : 2.83374, "percentage" : 3.85119 }
, { "name" : "res2a_branch2a + res2a_branch2a_relu", "timeMs" : 28.4745, "averageMs" : 0.632767, "percentage" : 0.859959 }
, { "name" : "res2a_branch2b + res2a_branch2b_relu", "timeMs" : 76.1654, "averageMs" : 1.69256, "percentage" : 2.30027 }
, { "name" : "res2a_branch2c", "timeMs" : 101.126, "averageMs" : 2.24725, "percentage" : 3.05412 }
, { "name" : "res2a_branch1 + res2a + res2a_relu", "timeMs" : 141.506, "averageMs" : 3.14458, "percentage" : 4.27363 }
, { "name" : "res2b_branch2a + res2b_branch2a_relu", "timeMs" : 63.1401, "averageMs" : 1.40311, "percentage" : 1.90689 }
, { "name" : "res2b_branch2b + res2b_branch2b_relu", "timeMs" : 77.8038, "averageMs" : 1.72897, "percentage" : 2.34975 }
, { "name" : "res2b_branch2c + res2b + res2b_relu", "timeMs" : 139.483, "averageMs" : 3.09963, "percentage" : 4.21254 }
, { "name" : "res2c_branch2a + res2c_branch2a_relu", "timeMs" : 64.1139, "averageMs" : 1.42475, "percentage" : 1.9363 }
, { "name" : "res2c_branch2b + res2c_branch2b_relu", "timeMs" : 76.3114, "averageMs" : 1.69581, "percentage" : 2.30468 }
, { "name" : "res2c_branch2c + res2c + res2c_relu", "timeMs" : 140.459, "averageMs" : 3.12132, "percentage" : 4.24201 }
, { "name" : "res3a_branch2a + res3a_branch2a_relu", "timeMs" : 24.6467, "averageMs" : 0.547705, "percentage" : 0.744355 }
, { "name" : "res3a_branch2b + res3a_branch2b_relu", "timeMs" : 63.5468, "averageMs" : 1.41215, "percentage" : 1.91918 }
, { "name" : "res3a_branch2c", "timeMs" : 69.411, "averageMs" : 1.54247, "percentage" : 2.09628 }
, { "name" : "res3a_branch1 + res3a + res3a_relu", "timeMs" : 111.751, "averageMs" : 2.48336, "percentage" : 3.375 }
, { "name" : "res3b_branch2a + res3b_branch2a_relu", "timeMs" : 39.1579, "averageMs" : 0.870177, "percentage" : 1.18261 }
, { "name" : "res3b_branch2b + res3b_branch2b_relu", "timeMs" : 62.7683, "averageMs" : 1.39485, "percentage" : 1.89567 }
, { "name" : "res3b_branch2c + res3b + res3b_relu", "timeMs" : 80.9717, "averageMs" : 1.79937, "percentage" : 2.44543 }
, { "name" : "res3c_branch2a + res3c_branch2a_relu", "timeMs" : 38.6562, "averageMs" : 0.859028, "percentage" : 1.16746 }
, { "name" : "res3c_branch2b + res3c_branch2b_relu", "timeMs" : 62.8339, "averageMs" : 1.39631, "percentage" : 1.89765 }
, { "name" : "res3c_branch2c + res3c + res3c_relu", "timeMs" : 79.7931, "averageMs" : 1.77318, "percentage" : 2.40983 }
, { "name" : "res3d_branch2a + res3d_branch2a_relu", "timeMs" : 38.9858, "averageMs" : 0.866351, "percentage" : 1.17741 }
, { "name" : "res3d_branch2b + res3d_branch2b_relu", "timeMs" : 62.6911, "averageMs" : 1.39314, "percentage" : 1.89333 }
, { "name" : "res3d_branch2c + res3d + res3d_relu", "timeMs" : 79.8137, "averageMs" : 1.77364, "percentage" : 2.41045 }
, { "name" : "res4a_branch2a + res4a_branch2a_relu", "timeMs" : 20.4268, "averageMs" : 0.453929, "percentage" : 0.61691 }
, { "name" : "res4a_branch2b + res4a_branch2b_relu", "timeMs" : 58.1213, "averageMs" : 1.29159, "percentage" : 1.75532 }
, { "name" : "res4a_branch2c", "timeMs" : 44.7633, "averageMs" : 0.994739, "percentage" : 1.35189 }
, { "name" : "res4a_branch1 + res4a + res4a_relu", "timeMs" : 80.3111, "averageMs" : 1.78469, "percentage" : 2.42547 }
, { "name" : "res4b_branch2a + res4b_branch2a_relu", "timeMs" : 30.5639, "averageMs" : 0.679198, "percentage" : 0.92306 }
, { "name" : "res4b_branch2b + res4b_branch2b_relu", "timeMs" : 58.8664, "averageMs" : 1.30814, "percentage" : 1.77782 }
, { "name" : "res4b_branch2c + res4b + res4b_relu", "timeMs" : 53.8298, "averageMs" : 1.19622, "percentage" : 1.62571 }
, { "name" : "res4c_branch2a + res4c_branch2a_relu", "timeMs" : 30.8903, "averageMs" : 0.686452, "percentage" : 0.932919 }
, { "name" : "res4c_branch2b + res4c_branch2b_relu", "timeMs" : 59.0933, "averageMs" : 1.31318, "percentage" : 1.78467 }
, { "name" : "res4c_branch2c + res4c + res4c_relu", "timeMs" : 54.3399, "averageMs" : 1.20755, "percentage" : 1.64112 }
, { "name" : "res4d_branch2a + res4d_branch2a_relu", "timeMs" : 30.5295, "averageMs" : 0.678433, "percentage" : 0.922021 }
, { "name" : "res4d_branch2b + res4d_branch2b_relu", "timeMs" : 57.9838, "averageMs" : 1.28853, "percentage" : 1.75117 }
, { "name" : "res4d_branch2c + res4d + res4d_relu", "timeMs" : 53.3468, "averageMs" : 1.18549, "percentage" : 1.61113 }
, { "name" : "res4e_branch2a + res4e_branch2a_relu", "timeMs" : 31.3923, "averageMs" : 0.697606, "percentage" : 0.948077 }
, { "name" : "res4e_branch2b + res4e_branch2b_relu", "timeMs" : 57.6237, "averageMs" : 1.28053, "percentage" : 1.74029 }
, { "name" : "res4e_branch2c + res4e + res4e_relu", "timeMs" : 53.572, "averageMs" : 1.19049, "percentage" : 1.61793 }
, { "name" : "res4f_branch2a + res4f_branch2a_relu", "timeMs" : 30.8669, "averageMs" : 0.685932, "percentage" : 0.932212 }
, { "name" : "res4f_branch2b + res4f_branch2b_relu", "timeMs" : 59.258, "averageMs" : 1.31684, "percentage" : 1.78965 }
, { "name" : "res4f_branch2c + res4f + res4f_relu", "timeMs" : 53.2732, "averageMs" : 1.18385, "percentage" : 1.6089 }
, { "name" : "res5a_branch2a + res5a_branch2a_relu", "timeMs" : 16.1121, "averageMs" : 0.358046, "percentage" : 0.4866 }
, { "name" : "res5a_branch2b + res5a_branch2b_relu", "timeMs" : 57.3952, "averageMs" : 1.27545, "percentage" : 1.73339 }
, { "name" : "res5a_branch2c", "timeMs" : 35.5885, "averageMs" : 0.790856, "percentage" : 1.07481 }
, { "name" : "res5a_branch1 + res5a + res5a_relu", "timeMs" : 67.503, "averageMs" : 1.50007, "percentage" : 2.03866 }
, { "name" : "res5b_branch2a + res5b_branch2a_relu", "timeMs" : 29.3268, "averageMs" : 0.651706, "percentage" : 0.885697 }
, { "name" : "res5b_branch2b + res5b_branch2b_relu", "timeMs" : 58.8418, "averageMs" : 1.3076, "percentage" : 1.77708 }
, { "name" : "res5b_branch2c + res5b + res5b_relu", "timeMs" : 40.3696, "averageMs" : 0.897101, "percentage" : 1.2192 }
, { "name" : "res5c_branch2a + res5c_branch2a_relu", "timeMs" : 28.9075, "averageMs" : 0.642389, "percentage" : 0.873036 }
, { "name" : "res5c_branch2b + res5c_branch2b_relu", "timeMs" : 58.4695, "averageMs" : 1.29932, "percentage" : 1.76584 }
, { "name" : "res5c_branch2c + res5c + res5c_relu", "timeMs" : 39.9923, "averageMs" : 0.888717, "percentage" : 1.20781 }
, { "name" : "pool5", "timeMs" : 11.4307, "averageMs" : 0.254015, "percentage" : 0.345217 }
, { "name" : "fc1000 input reformatter 0", "timeMs" : 1.51405, "averageMs" : 0.0336455, "percentage" : 0.0457257 }
, { "name" : "fc1000", "timeMs" : 18.0076, "averageMs" : 0.400168, "percentage" : 0.543846 }
, { "name" : "prob", "timeMs" : 1.14147, "averageMs" : 0.025366, "percentage" : 0.0344736 }
]
[
  { "count" : 15 }
, { "name" : "conv1 + conv1_relu + pool1 input reformatter 0", "timeMs" : 85.8941, "averageMs" : 5.72628, "percentage" : 2.32559 }
, { "name" : "conv1 + conv1_relu + pool1", "timeMs" : 146.487, "averageMs" : 9.76577, "percentage" : 3.96614 }
, { "name" : "res2a_branch2a + res2a_branch2a_relu", "timeMs" : 28.0828, "averageMs" : 1.87219, "percentage" : 0.760344 }
, { "name" : "res2a_branch2b + res2a_branch2b_relu", "timeMs" : 88.0207, "averageMs" : 5.86805, "percentage" : 2.38317 }
, { "name" : "res2a_branch2c", "timeMs" : 108.76, "averageMs" : 7.25069, "percentage" : 2.9447 }
, { "name" : "res2a_branch1 + res2a + res2a_relu", "timeMs" : 158.751, "averageMs" : 10.5834, "percentage" : 4.29821 }
, { "name" : "res2b_branch2a + res2b_branch2a_relu", "timeMs" : 70.8323, "averageMs" : 4.72215, "percentage" : 1.91779 }
, { "name" : "res2b_branch2b + res2b_branch2b_relu", "timeMs" : 82.6505, "averageMs" : 5.51003, "percentage" : 2.23777 }
, { "name" : "res2b_branch2c + res2b + res2b_relu", "timeMs" : 158.138, "averageMs" : 10.5425, "percentage" : 4.2816 }
, { "name" : "res2c_branch2a + res2c_branch2a_relu", "timeMs" : 72.7856, "averageMs" : 4.85238, "percentage" : 1.97068 }
, { "name" : "res2c_branch2b + res2c_branch2b_relu", "timeMs" : 80.9313, "averageMs" : 5.39542, "percentage" : 2.19122 }
, { "name" : "res2c_branch2c + res2c + res2c_relu", "timeMs" : 158.461, "averageMs" : 10.5641, "percentage" : 4.29035 }
, { "name" : "res3a_branch2a + res3a_branch2a_relu", "timeMs" : 27.0952, "averageMs" : 1.80635, "percentage" : 0.733606 }
, { "name" : "res3a_branch2b + res3a_branch2b_relu", "timeMs" : 72.3044, "averageMs" : 4.82029, "percentage" : 1.95765 }
, { "name" : "res3a_branch2c", "timeMs" : 74.618, "averageMs" : 4.97453, "percentage" : 2.02029 }
, { "name" : "res3a_branch1 + res3a + res3a_relu", "timeMs" : 126.156, "averageMs" : 8.41038, "percentage" : 3.41568 }
, { "name" : "res3b_branch2a + res3b_branch2a_relu", "timeMs" : 44.6654, "averageMs" : 2.97769, "percentage" : 1.20932 }
, { "name" : "res3b_branch2b + res3b_branch2b_relu", "timeMs" : 71.5857, "averageMs" : 4.77238, "percentage" : 1.93819 }
, { "name" : "res3b_branch2c + res3b + res3b_relu", "timeMs" : 86.2679, "averageMs" : 5.7512, "percentage" : 2.33571 }
, { "name" : "res3c_branch2a + res3c_branch2a_relu", "timeMs" : 42.1451, "averageMs" : 2.80967, "percentage" : 1.14108 }
, { "name" : "res3c_branch2b + res3c_branch2b_relu", "timeMs" : 70.5358, "averageMs" : 4.70239, "percentage" : 1.90976 }
, { "name" : "res3c_branch2c + res3c + res3c_relu", "timeMs" : 89.376, "averageMs" : 5.9584, "percentage" : 2.41986 }
, { "name" : "res3d_branch2a + res3d_branch2a_relu", "timeMs" : 42.2497, "averageMs" : 2.81665, "percentage" : 1.14392 }
, { "name" : "res3d_branch2b + res3d_branch2b_relu", "timeMs" : 70.3664, "averageMs" : 4.69109, "percentage" : 1.90518 }
, { "name" : "res3d_branch2c + res3d + res3d_relu", "timeMs" : 92.2302, "averageMs" : 6.14868, "percentage" : 2.49714 }
, { "name" : "res4a_branch2a + res4a_branch2a_relu", "timeMs" : 20.3042, "averageMs" : 1.35361, "percentage" : 0.549739 }
, { "name" : "res4a_branch2b + res4a_branch2b_relu", "timeMs" : 61.6269, "averageMs" : 4.10846, "percentage" : 1.66855 }
, { "name" : "res4a_branch2c", "timeMs" : 53.1897, "averageMs" : 3.54598, "percentage" : 1.44012 }
, { "name" : "res4a_branch1 + res4a + res4a_relu", "timeMs" : 89.5329, "averageMs" : 5.96886, "percentage" : 2.42411 }
, { "name" : "res4b_branch2a + res4b_branch2a_relu", "timeMs" : 35.9427, "averageMs" : 2.39618, "percentage" : 0.973152 }
, { "name" : "res4b_branch2b + res4b_branch2b_relu", "timeMs" : 62.7624, "averageMs" : 4.18416, "percentage" : 1.6993 }
, { "name" : "res4b_branch2c + res4b + res4b_relu", "timeMs" : 64.1746, "averageMs" : 4.27831, "percentage" : 1.73753 }
, { "name" : "res4c_branch2a + res4c_branch2a_relu", "timeMs" : 32.2735, "averageMs" : 2.15157, "percentage" : 0.873809 }
, { "name" : "res4c_branch2b + res4c_branch2b_relu", "timeMs" : 65.3051, "averageMs" : 4.35367, "percentage" : 1.76814 }
, { "name" : "res4c_branch2c + res4c + res4c_relu", "timeMs" : 59.1519, "averageMs" : 3.94346, "percentage" : 1.60154 }
, { "name" : "res4d_branch2a + res4d_branch2a_relu", "timeMs" : 36.3166, "averageMs" : 2.42111, "percentage" : 0.983275 }
, { "name" : "res4d_branch2b + res4d_branch2b_relu", "timeMs" : 62.2427, "averageMs" : 4.14951, "percentage" : 1.68523 }
, { "name" : "res4d_branch2c + res4d + res4d_relu", "timeMs" : 63.5095, "averageMs" : 4.23397, "percentage" : 1.71953 }
, { "name" : "res4e_branch2a + res4e_branch2a_relu", "timeMs" : 31.933, "averageMs" : 2.12887, "percentage" : 0.864589 }
, { "name" : "res4e_branch2b + res4e_branch2b_relu", "timeMs" : 67.478, "averageMs" : 4.49853, "percentage" : 1.82697 }
, { "name" : "res4e_branch2c + res4e + res4e_relu", "timeMs" : 58.5616, "averageMs" : 3.9041, "percentage" : 1.58556 }
, { "name" : "res4f_branch2a + res4f_branch2a_relu", "timeMs" : 35.4907, "averageMs" : 2.36605, "percentage" : 0.960914 }
, { "name" : "res4f_branch2b + res4f_branch2b_relu", "timeMs" : 63.5359, "averageMs" : 4.23573, "percentage" : 1.72024 }
, { "name" : "res4f_branch2c + res4f + res4f_relu", "timeMs" : 64.0117, "averageMs" : 4.26745, "percentage" : 1.73312 }
, { "name" : "res5a_branch2a + res5a_branch2a_relu", "timeMs" : 17.1984, "averageMs" : 1.14656, "percentage" : 0.465649 }
, { "name" : "res5a_branch2b + res5a_branch2b_relu", "timeMs" : 65.6974, "averageMs" : 4.37983, "percentage" : 1.77876 }
, { "name" : "res5a_branch2c", "timeMs" : 43.0779, "averageMs" : 2.87186, "percentage" : 1.16634 }
, { "name" : "res5a_branch1 + res5a + res5a_relu", "timeMs" : 71.569, "averageMs" : 4.77127, "percentage" : 1.93774 }
, { "name" : "res5b_branch2a + res5b_branch2a_relu", "timeMs" : 30.6329, "averageMs" : 2.0422, "percentage" : 0.82939 }
, { "name" : "res5b_branch2b + res5b_branch2b_relu", "timeMs" : 65.7444, "averageMs" : 4.38296, "percentage" : 1.78004 }
, { "name" : "res5b_branch2c + res5b + res5b_relu", "timeMs" : 45.1072, "averageMs" : 3.00715, "percentage" : 1.22128 }
, { "name" : "res5c_branch2a + res5c_branch2a_relu", "timeMs" : 32.7235, "averageMs" : 2.18157, "percentage" : 0.885992 }
, { "name" : "res5c_branch2b + res5c_branch2b_relu", "timeMs" : 65.7613, "averageMs" : 4.38409, "percentage" : 1.78049 }
, { "name" : "res5c_branch2c + res5c + res5c_relu", "timeMs" : 43.4207, "averageMs" : 2.89472, "percentage" : 1.17562 }
, { "name" : "pool5", "timeMs" : 15.0802, "averageMs" : 1.00534, "percentage" : 0.408297 }
, { "name" : "fc1000 input reformatter 0", "timeMs" : 0.870336, "averageMs" : 0.0580224, "percentage" : 0.0235644 }
, { "name" : "fc1000", "timeMs" : 19.2125, "averageMs" : 1.28083, "percentage" : 0.52018 }
, { "name" : "prob", "timeMs" : 0.600896, "averageMs" : 0.0400597, "percentage" : 0.0162693 }
]
